MANIFEST.in
setup.cfg
setup.py
creaturecast_project/__init__.py
creaturecast_project/asset.py
creaturecast_project/functions.py
creaturecast_project.egg-info/PKG-INFO
creaturecast_project.egg-info/SOURCES.txt
creaturecast_project.egg-info/dependency_links.txt
creaturecast_project.egg-info/requires.txt
creaturecast_project.egg-info/top_level.txt
creaturecast_project/data/__init__.py
creaturecast_project/data/data_types.py
creaturecast_project/data/project_objects.py
creaturecast_project/data/projects.py
creaturecast_project/tests/__init__.py
creaturecast_project/tests/test_all.py
creaturecast_project/tests/test_data.py