Metadata-Version: 1.1
Name: creaturecast-project
Version: 0.0.5
Summary: Base classes for projects, assets and components
Home-page: https://github.com/Paxtongerrish/creaturecast_project.git
Author: Paxton Gerrish
Author-email: creaturecastlabs@gmail.com
License: UNKNOWN
Keywords: sample setuptools development
Platform: UNKNOWN
Classifier: Development Status :: 3 - Alpha
Classifier: Intended Audience :: End Users/Desktop
Classifier: Topic :: Software Development :: Build Tools
Classifier: License :: OSI Approved :: MIT License
Classifier: Programming Language :: Python :: 2.7
